django_force_disable_permissions_admin
django_force_disable_permissions_admin_demo
django_force_disable_permissions_admin_example
